radiusdesk_api/__init__.py
radiusdesk_api/auth.py
radiusdesk_api/client.py
radiusdesk_api/exceptions.py
radiusdesk_api/users.py
radiusdesk_api/utils.py
radiusdesk_api/vouchers.py
radiusdesk_api-0.3.0.dist-info/licenses/LICENSE
radiusdesk_api-0.3.0.dist-info/METADATA
radiusdesk_api-0.3.0.dist-info/WHEEL
radiusdesk_api-0.3.0.dist-info/top_level.txt
radiusdesk_api-0.3.0.dist-info/RECORD
