Metadata-Version: 2.4
Name: radiusdesk-api
Version: 0.3.0
Summary: Python client for RADIUSdesk API - manage vouchers, users, and balances
Home-page: https://github.com/keeganwhite/radiusdesk-api
Author: Keegan White
Author-email: Keegan White <keeganthomaswhite@gmail.com.com>
License-Expression: GPL-3.0-or-later
Project-URL: Homepage, https://github.com/keeganwhite/radiusdesk-api
Project-URL: Documentation, https://github.com/keeganwhite/radiusdesk-api#readme
Project-URL: Repository, https://github.com/keeganwhite/radiusdesk-api
Project-URL: Issues, https://github.com/keeganwhite/radiusdesk-api/issues
Keywords: radiusdesk,api,voucher,radius,authentication
Classifier: Development Status :: 3 - Alpha
Classifier: Intended Audience :: Developers
Classifier: Operating System :: OS Independent
Classifier: Programming Language :: Python :: 3
Classifier: Programming Language :: Python :: 3.10
Classifier: Programming Language :: Python :: 3.11
Classifier: Programming Language :: Python :: 3.12
Classifier: Topic :: Software Development :: Libraries :: Python Modules
Requires-Python: >=3.10
License-File: LICENSE
Requires-Dist: requests>=2.31.0
Provides-Extra: dev
Requires-Dist: pytest>=7.4.0; extra == "dev"
Requires-Dist: flake8>=6.0.0; extra == "dev"
Requires-Dist: build>=0.10.0; extra == "dev"
Requires-Dist: twine>=4.0.0; extra == "dev"
Requires-Dist: python-dotenv>=1.0.0; extra == "dev"
Dynamic: license-file
